openschc/VERSION.py
openschc/__init__.py
openschc/__main__.py
openschc-0.0.3.dist-info/AUTHORS.txt
openschc-0.0.3.dist-info/LICENSE
openschc-0.0.3.dist-info/METADATA
openschc-0.0.3.dist-info/WHEEL
openschc-0.0.3.dist-info/entry_points.txt
openschc-0.0.3.dist-info/top_level.txt
openschc-0.0.3.dist-info/RECORD
