Metadata-Version: 2.1
Name: openschc
Version: 0.0.3
Summary: open-source implementation of SCHC (Static Context Header Compression)
Home-page: https://github.com/openschc/openschc
Author: Thomas Watteyne
Author-email: twatteyne@gmail.com
Project-URL: Source Code, https://github.com/openschc/openschc
Project-URL: Bug Tracker, https://github.com/openschc/openschc/issues
Classifier: Programming Language :: Python :: 3
Classifier: License :: OSI Approved :: MIT License
Classifier: Operating System :: OS Independent
License-File: LICENSE
License-File: AUTHORS.txt
Requires-Dist: kamene
